geci_janitor/__init__.py
geci_janitor/cli.py
geci_janitor-0.14.0.dist-info/entry_points.txt
geci_janitor-0.14.0.dist-info/licenses/LICENSE
geci_janitor-0.14.0.dist-info/WHEEL
geci_janitor-0.14.0.dist-info/METADATA
geci_janitor-0.14.0.dist-info/RECORD
