Metadata-Version: 2.4
Name: geci_janitor
Version: 0.14.0
Summary: Module to clean and process GECI data
Home-page: https://github.com/IslasGECI/janitor
Author: Ciencia de Datos • GECI
Author-email: ciencia.datos@islas.org.mx
Requires-Python: >=3.9
Classifier: License :: OSI Approved :: GNU General Public License v3 or later (GPLv3+)
License-File: LICENSE
Requires-Dist: typer[all]
